wizprint/__init__.py
wizprint/__main__.py
wizprint/console.py
wizprint-1.1.1.dist-info/METADATA
wizprint-1.1.1.dist-info/WHEEL
wizprint-1.1.1.dist-info/entry_points.txt
wizprint-1.1.1.dist-info/top_level.txt
wizprint-1.1.1.dist-info/RECORD
