Metadata-Version: 2.1
Name: wizprint
Version: 1.1.1
Summary: for Python3 + Console: wprint; A Small Gimmick that makes printing tasks to console just a bit more fun by introducing a Wizard that will tell you your customized message in a bubble. | fnt; Adds Console Coloring and Emojis for wprint.
Home-page: https://github.com/NamasteJasutin/wizprint
Author: NamasteJasutin
Author-email: justin.duijn@outlook.com
License: MIT
Platform: UNKNOWN
Classifier: License :: OSI Approved :: MIT License
Classifier: Programming Language :: Python :: 3
Classifier: Programming Language :: Python :: 3.7
Classifier: Operating System :: OS Independent
